nonebot_plugin_omikuji/__init__.py
nonebot_plugin_omikuji/cache.py
nonebot_plugin_omikuji/commands.py
nonebot_plugin_omikuji/config.py
nonebot_plugin_omikuji/llm_tool.py
nonebot_plugin_omikuji/models.py
nonebot_plugin_omikuji/sql_models.py
nonebot_plugin_omikuji/utils.py
nonebot_plugin_omikuji-0.1.3.dist-info/licenses/LICENSE
nonebot_plugin_omikuji-0.1.3.dist-info/METADATA
nonebot_plugin_omikuji-0.1.3.dist-info/WHEEL
nonebot_plugin_omikuji-0.1.3.dist-info/top_level.txt
nonebot_plugin_omikuji-0.1.3.dist-info/RECORD
